configdot/__init__.py
configdot/configdot.py
configdot/utils.py
configdot-0.144.dist-info/LICENSE
configdot-0.144.dist-info/METADATA
configdot-0.144.dist-info/WHEEL
configdot-0.144.dist-info/top_level.txt
configdot-0.144.dist-info/RECORD
