Metadata-Version: 2.1
Name: configdot
Version: 0.144
Summary: Config object with attribute access and INI parser
Home-page: https://github.com/jjnurminen/configdot
Author: Jussi Nurminen
Author-email: jnu@iki.fi
License: GPLv3
Platform: UNKNOWN
License-File: LICENSE
